procustodibus_broker/__init__.py
procustodibus_broker/api.py
procustodibus_broker/broker.py
procustodibus_broker/cli.py
procustodibus_broker/cnf.py
procustodibus_broker/connectivity.py
procustodibus_broker/credentials.py
procustodibus_broker/pipe.py
procustodibus_broker-1.1.1.dist-info/LICENSE
procustodibus_broker-1.1.1.dist-info/METADATA
procustodibus_broker-1.1.1.dist-info/WHEEL
procustodibus_broker-1.1.1.dist-info/entry_points.txt
procustodibus_broker-1.1.1.dist-info/top_level.txt
procustodibus_broker-1.1.1.dist-info/zip-safe
procustodibus_broker-1.1.1.dist-info/RECORD
