Metadata-Version: 2.1
Name: procustodibus_broker
Version: 1.1.1
Summary: Pushes events from Pro Custodibus into your security management systems.
Home-page: https://www.procustodibus.com/
Author: Arcem Tene
Author-email: dev@arcemtene.com
License: MIT
Project-URL: Changelog, https://docs.procustodibus.com/guide/integrations/brokers/#changelog
Project-URL: Documentation, https://docs.procustodibus.com/guide/integrations/brokers/
Project-URL: Source, https://git.sr.ht/~arx10/procustodibus-broker
Project-URL: Tracker, https://todo.sr.ht/~arx10/procustodibus
Classifier: Development Status :: 5 - Production/Stable
Classifier: Intended Audience :: System Administrators
Classifier: Topic :: System :: Networking :: Monitoring
Classifier: License :: OSI Approved :: MIT License
Classifier: Programming Language :: Python :: 3.8
Classifier: Programming Language :: Python :: 3.9
Classifier: Programming Language :: Python :: 3.10
Classifier: Programming Language :: Python :: 3.11
Classifier: Programming Language :: Python :: 3.12
Requires-Python: >=3.8
License-File: LICENSE
Requires-Dist: docopt-ng ~=0.9
Requires-Dist: inflection ~=0.5
Requires-Dist: pynacl ~=1.5
Requires-Dist: requests ~=2.31
Provides-Extra: lint
Requires-Dist: cohesion ; extra == 'lint'
Requires-Dist: darglint ; extra == 'lint'
Requires-Dist: dlint ; extra == 'lint'
Requires-Dist: flake8 ; extra == 'lint'
Requires-Dist: flake8-alfred ; extra == 'lint'
Requires-Dist: flake8-bandit ; extra == 'lint'
Requires-Dist: flake8-broken-line ; extra == 'lint'
Requires-Dist: flake8-bugbear ; extra == 'lint'
Requires-Dist: flake8-builtins ; extra == 'lint'
Requires-Dist: flake8-class-attributes-order ; extra == 'lint'
Requires-Dist: flake8-coding ; extra == 'lint'
Requires-Dist: flake8-cognitive-complexity ; extra == 'lint'
Requires-Dist: flake8-comprehensions ; extra == 'lint'
Requires-Dist: flake8-debugger ; extra == 'lint'
Requires-Dist: flake8-docstrings ; extra == 'lint'
Requires-Dist: flake8-eradicate ; extra == 'lint'
Requires-Dist: flake8-executable ; extra == 'lint'
Requires-Dist: flake8-expression-complexity ; extra == 'lint'
Requires-Dist: flake8-functions ; extra == 'lint'
Requires-Dist: flake8-fixme ; extra == 'lint'
Requires-Dist: flake8-isort ; extra == 'lint'
Requires-Dist: flake8-logging-format ; extra == 'lint'
Requires-Dist: flake8-pep3101 ; extra == 'lint'
Requires-Dist: flake8-print ; extra == 'lint'
Requires-Dist: flake8-pytest ; extra == 'lint'
Requires-Dist: flake8-pytest-style ; extra == 'lint'
Requires-Dist: flake8-requirements ; extra == 'lint'
Requires-Dist: flake8-rst ; extra == 'lint'
Requires-Dist: flake8-spellcheck ; extra == 'lint'
Requires-Dist: flake8-string-format ; extra == 'lint'
Requires-Dist: pep8-naming ; extra == 'lint'
Provides-Extra: test
Requires-Dist: pytest ; extra == 'test'
Requires-Dist: pytest-cov ; extra == 'test'
Requires-Dist: pytest-datadir ; extra == 'test'
Requires-Dist: pytest-mock ; extra == 'test'
Requires-Dist: pytest-timeout ; extra == 'test'
Requires-Dist: pytest-watch ; extra == 'test'
